Metadata-Version: 2.1
Name: hack4u-Silv
Version: 0.1.1
Summary: Library for hack4u courses
Home-page: https://hack4u.io
Author: Polsiv
